aau_label-0.3.9.dist-info/METADATA
aau_label-0.3.9.dist-info/WHEEL
aau_label-0.3.9.dist-info/entry_points.txt
aau_label-0.3.9.dist-info/licenses/LICENSE
aau_label/__init__.py
aau_label/errors.py
aau_label/io/__init__.py
aau_label/io/darknet.py
aau_label/io/pascal.py
aau_label/model.py
aau_label/parsers/__init__.py
aau_label/parsers/darknet_parser.py
aau_label/parsers/pascal_parser.py
aau_label/protocols.py
aau_label/utilities.py
aau_label-0.3.9.dist-info/RECORD
