Metadata-Version: 2.1
Name: aau-label
Version: 0.3.9
Summary: A image labeling handler
Author-Email: Kasper Fromm Pedersen <kasperfromm@protonmail.com>
License: MIT
Requires-Python: <3.13,>=3.10
Requires-Dist: pillow==10.*
Requires-Dist: pandas==2.2.*
Requires-Dist: typing-extensions>=4.5.0
